townsnet/__init__.py
townsnet/base_schema.py
townsnet/voronizer.py
townsnet/engineering/__init__.py
townsnet/engineering/engineer_potential.py
townsnet/engineering/engineering_model.py
townsnet/potential/__init__.py
townsnet/potential/grid_generator.py
townsnet/potential/indicator.py
townsnet/potential/potential_model.py
townsnet/potential/profile.py
townsnet/provision/__init__.py
townsnet/provision/provision_model.py
townsnet/provision/service_type.py
townsnet/provision/social_model.py
townsnet-0.0.10.dist-info/licenses/LICENSE
townsnet-0.0.10.dist-info/METADATA
townsnet-0.0.10.dist-info/WHEEL
townsnet-0.0.10.dist-info/top_level.txt
townsnet-0.0.10.dist-info/RECORD
