Metadata-Version: 2.4
Name: townsnet
Version: 0.0.10
Summary: Provision assessment for cities of an urban region
Author-email: Vasilii Starikov <vasilstar97@gmail.com>
License: BSD 3-Clause License
Project-URL: Repository, https://github.com/vasilstar97/townsnet
Project-URL: Bug Tracker, https://github.com/vasilstar97/townsnet/issues
Classifier: Programming Language :: Python :: 3
Classifier: License :: OSI Approved :: BSD License
Classifier: Operating System :: OS Independent
Classifier: Intended Audience :: Science/Research
Requires-Python: >=3.10
License-File: LICENSE
Requires-Dist: geopandas<2.0.0,>=1.0.0
Requires-Dist: pandas<3.0.0,>=1.5.3
Requires-Dist: loguru<1.0.0,>=0.7.0
Requires-Dist: osmnx<2.0.0,>=1.6.0
Requires-Dist: PuLP==2.7.0
Requires-Dist: pandera
Requires-Dist: pyarrow>=12.0.0
Requires-Dist: pydantic
Requires-Dist: shapely
Requires-Dist: tqdm<5.0.0,>=4.65.0
Requires-Dist: h3<4.0.0,>=3.6.1
Provides-Extra: dev
Requires-Dist: black[jupyter]>=22; extra == "dev"
Requires-Dist: mapclassify==2.6.1; extra == "dev"
Requires-Dist: folium==0.14.0; extra == "dev"
Requires-Dist: matplotlib; extra == "dev"
Requires-Dist: matplotlib-inline==0.1.6; extra == "dev"
Requires-Dist: ipykernel; extra == "dev"
Requires-Dist: jupyter; extra == "dev"
Requires-Dist: ipywidgets; extra == "dev"
Requires-Dist: isort>=5.6; extra == "dev"
Requires-Dist: pylint>=2.17; extra == "dev"
Requires-Dist: pre-commit>=3.1; extra == "dev"
Requires-Dist: pytest==7.4.3; extra == "dev"
Requires-Dist: pytest-cov==4.1.0; extra == "dev"
Requires-Dist: build; extra == "dev"
Requires-Dist: twine; extra == "dev"
Dynamic: license-file
